anyleaf/__init__.py
anyleaf/filter.py
anyleaf-0.1.9.dist-info/LICENSE
anyleaf-0.1.9.dist-info/METADATA
anyleaf-0.1.9.dist-info/WHEEL
anyleaf-0.1.9.dist-info/top_level.txt
anyleaf-0.1.9.dist-info/RECORD
