Metadata-Version: 2.1
Name: anyleaf
Version: 0.1.9
Summary: Driver for the Anyleaf pH sensor
Home-page: https://anyleaf.org
Author: Anyleaf
Author-email: anyleaf@anyleaf.org
License: MIT
Platform: UNKNOWN
Classifier: Programming Language :: Python :: 3
Classifier: Operating System :: OS Independent
Classifier: Topic :: System :: Hardware :: Hardware Drivers 
Requires-Python: >=3.7
Requires-Dist: adafruit-circuitpython-ads1x15 (>=2.2.2)
Requires-Dist: adafruit-circuitpython-max31865 (>=2.2.3)
Requires-Dist: filterpy (>=1.4.5)
Requires-Dist: pyserial (>=3.4)
